[{"d":"Mar-08-23","act":"Upgrade","a":"Argus","ch":"Hold","ch2":"Buy","pr":23,"pr_old":0},{"d":"Feb-03-23","act":"Upgrade","a":"Gordon Haskett","ch":"Reduce","ch2":"Hold","pr":22,"pr_old":0},{"d":"Jan-30-23","act":"Initiated","a":"Goldman","ch":"Neutral","ch2":"","pr":20,"pr_old":0},{"d":"Jan-20-23","act":"Downgrade","a":"Gordon Haskett","ch":"Hold","ch2":"Reduce","pr":13,"pr_old":20},{"d":"Jan-05-23","act":"Downgrade","a":"Piper Sandler","ch":"Overweight","ch2":"Neutral","pr":20,"pr_old":26},{"d":"Sep-15-22","act":"Upgrade","a":"Jefferies","ch":"Hold","ch2":"Buy","pr":24,"pr_old":21},{"d":"Jul-22-22","act":"Initiated","a":"Piper Sandler","ch":"Overweight","ch2":"","pr":28,"pr_old":0},{"d":"Jul-21-22","act":"Initiated","a":"KeyBanc Capital Markets","ch":"Overweight","ch2":"","pr":30,"pr_old":0},{"d":"Mar-02-22","act":"Reiterated","a":"Telsey Advisory Group","ch":"Market Perform","ch2":"","pr":30,"pr_old":27},{"d":"Mar-02-22","act":"Reiterated","a":"Credit Suisse","ch":"Neutral","ch2":"","pr":29,"pr_old":26},{"d":"Mar-02-22","act":"Reiterated","a":"Cowen","ch":"Market Perform","ch2":"","pr":30,"pr_old":25},{"d":"Mar-02-22","act":"Reiterated","a":"BMO Capital Markets","ch":"Market Perform","ch2":"","pr":30,"pr_old":23},{"d":"Feb-16-22","act":"Downgrade","a":"Evercore ISI","ch":"Outperform","ch2":"In-line","pr":0,"pr_old":0},{"d":"Nov-24-21","act":"Downgrade","a":"Jefferies","ch":"Buy","ch2":"Hold","pr":30,"pr_old":48},{"d":"Nov-11-21","act":"Downgrade","a":"Gordon Haskett","ch":"Buy","ch2":"Hold","pr":0,"pr_old":0},{"d":"Aug-26-21","act":"Downgrade","a":"Morgan Stanley","ch":"Equal-Weight","ch2":"Underweight","pr":27,"pr_old":36},{"d":"Aug-25-21","act":"Downgrade","a":"JP Morgan","ch":"Neutral","ch2":"Underweight","pr":34,"pr_old":0},{"d":"May-26-21","act":"Reiterated","a":"Telsey Advisory Group","ch":"Market Perform","ch2":"","pr":36,"pr_old":44},{"d":"May-19-21","act":"Reiterated","a":"Telsey Advisory Group","ch":"Market Perform","ch2":"","pr":44,"pr_old":38},{"d":"Mar-12-21","act":"Initiated","a":"Jefferies","ch":"Buy","ch2":"","pr":48,"pr_old":0}]