[{"d":"Jun-13-23","act":"Reiterated","a":"Guggenheim","ch":"Buy","ch2":"","pr":500,"pr_old":375},{"d":"Jun-13-23","act":"Reiterated","a":"BofA Securities","ch":"Buy","ch2":"","pr":490,"pr_old":410},{"d":"Apr-19-23","act":"Upgrade","a":"UBS","ch":"Neutral","ch2":"Buy","pr":390,"pr_old":350},{"d":"Apr-19-23","act":"Reiterated","a":"Rosenblatt","ch":"Neutral","ch2":"","pr":357,"pr_old":345},{"d":"Apr-19-23","act":"Reiterated","a":"Pivotal Research Group","ch":"Buy","ch2":"","pr":425,"pr_old":400},{"d":"Apr-19-23","act":"Reiterated","a":"Piper Sandler","ch":"Neutral","ch2":"","pr":350,"pr_old":325},{"d":"Apr-19-23","act":"Reiterated","a":"JP Morgan","ch":"Overweight","ch2":"","pr":380,"pr_old":390},{"d":"Apr-19-23","act":"Reiterated","a":"Jefferies","ch":"Buy","ch2":"","pr":405,"pr_old":415},{"d":"Apr-19-23","act":"Reiterated","a":"Deutsche Bank","ch":"Buy","ch2":"","pr":410,"pr_old":400},{"d":"Apr-11-23","act":"Resumed","a":"Robert W. Baird","ch":"Neutral","ch2":"","pr":340,"pr_old":0},{"d":"Jan-23-23","act":"Reiterated","a":"Argus","ch":"Buy","ch2":"","pr":390,"pr_old":340},{"d":"Jan-20-23","act":"Reiterated","a":"Wolfe Research","ch":"Outperform","ch2":"","pr":417,"pr_old":366},{"d":"Jan-20-23","act":"Reiterated","a":"Wedbush","ch":"Outperform","ch2":"","pr":410,"pr_old":400},{"d":"Jan-20-23","act":"Reiterated","a":"The Benchmark Company","ch":"Sell","ch2":"","pr":250,"pr_old":225},{"d":"Jan-20-23","act":"Reiterated","a":"Robert W. Baird","ch":"Neutral","ch2":"","pr":325,"pr_old":275},{"d":"Jan-20-23","act":"Reiterated","a":"Pivotal Research Group","ch":"Buy","ch2":"","pr":400,"pr_old":375},{"d":"Jan-20-23","act":"Reiterated","a":"Piper Sandler","ch":"Neutral","ch2":"","pr":325,"pr_old":270},{"d":"Jan-20-23","act":"Reiterated","a":"Oppenheimer","ch":"Outperform","ch2":"","pr":415,"pr_old":400},{"d":"Jan-20-23","act":"Reiterated","a":"MoffettNathanson","ch":"Market Perform","ch2":"","pr":250,"pr_old":240},{"d":"Jan-20-23","act":"Reiterated","a":"Jefferies","ch":"Buy","ch2":"","pr":400,"pr_old":385}]