{"tm":1686890335,"s":"MU","news":[{"t":"Micron Vows $600 Million China Investment Weeks After Chip Ban","dt":"Jun-15-23 11:22PM","a":"Bloomberg","u":"https:\/\/finance.yahoo.com\/news\/micron-vows-600-million-china-032224146.html"},{"t":"Micron (MU) Gains But Lags Market: What You Should Know","dt":"Jun-13-23 05:45PM","a":"Zacks","u":"https:\/\/finance.yahoo.com\/news\/micron-mu-gains-lags-market-214520992.html"},{"t":"Micron (MU) Inks Power Purchase Contract With Terra-Gen","dt":"Jun-12-23 10:29AM","a":"Zacks","u":"https:\/\/finance.yahoo.com\/news\/micron-mu-inks-power-purchase-142900729.html"},{"t":"Nvidia Stock Is Expensive, But This AI Stock Could Become a Screaming Bargain in June","dt":"05:05AM","a":"Motley Fool","u":"https:\/\/finance.yahoo.com\/m\/e3c81bf1-c23c-3886-83fc-bf008a1d7da6\/nvidia-stock-is-expensive%2C.html"},{"t":"Micron (MU) Avails High-Speed DDR5 RDIMMs Volume Production","dt":"09:32AM","a":"Zacks","u":"https:\/\/finance.yahoo.com\/news\/micron-mu-avails-high-speed-133200903.html"},{"t":"Micron (MU) Dips More Than Broader Markets: What You Should Know","dt":"Jun-07-23 05:45PM","a":"Zacks","u":"https:\/\/finance.yahoo.com\/news\/micron-mu-dips-more-broader-214516244.html"},{"t":"12 Hot Stocks to Buy According to Hedge Funds","dt":"08:15AM","a":"Insider Monkey","u":"https:\/\/finance.yahoo.com\/news\/12-hot-stocks-buy-according-121521749.html"},{"t":"Micron Is the Top Chip Stock Pick Amid AI Hype, Says Analyst","dt":"Jun-05-23 12:40PM","a":"Barrons.com","u":"https:\/\/finance.yahoo.com\/m\/09af6f14-e1ac-3645-8d28-75a508bb9b34\/micron-is-the-top-chip-stock.html"},{"t":"House lawmakers urge US to rally allies over China Micron ban","dt":"Jun-02-23 03:19PM","a":"Reuters","u":"https:\/\/finance.yahoo.com\/news\/house-lawmakers-urge-us-rally-191909665.html"},{"t":"Micron (MU) Outpaces Stock Market Gains: What You Should Know","dt":"Jun-01-23 05:45PM","a":"Zacks","u":"https:\/\/finance.yahoo.com\/news\/micron-mu-outpaces-stock-market-214519786.html"},{"t":"Micron Breaks Ground on Childcare Center in Idaho as Part of Idaho Community Investment Framework","dt":"May-31-23 11:00AM","a":"GlobeNewswire","u":"https:\/\/finance.yahoo.com\/news\/micron-breaks-ground-childcare-center-150000738.html"},{"t":"US 'won't tolerate' China's ban on chipmaker Micron","dt":"May-28-23 09:12PM","a":"Fox Business","u":"https:\/\/finance.yahoo.com\/news\/us-wont-tolerate-chinas-ban-011244768.html"},{"t":"U.S. 'won't tolerate' China's ban on Micron chips-Raimondo","dt":"01:40PM","a":"Reuters","u":"https:\/\/finance.yahoo.com\/news\/u-wont-tolerate-chinas-ban-174005566.html"},{"t":"Micron Seeks Other Avenues for Growth Amidst China's Ban","dt":"12:33PM","a":"GuruFocus.com","u":"https:\/\/finance.yahoo.com\/news\/micron-seeks-other-avenues-growth-163336924.html"},{"t":"Tech war: China's top server makers stop orders of memory modules containing Micron chips, sources say","dt":"05:30AM","a":"South China Morning Post","u":"https:\/\/finance.yahoo.com\/news\/tech-war-chinas-top-server-093000088.html"},{"t":"Nvidia stock soars on earnings, AI developments","dt":"03:22PM","a":"Yahoo Finance Video","u":"https:\/\/finance.yahoo.com\/video\/nvidia-stock-soars-earnings-ai-192218971.html"},{"t":"US-China trade war: officials to take another run at restarting trade talks, easing tensions","dt":"05:30AM","a":"South China Morning Post","u":"https:\/\/finance.yahoo.com\/news\/us-china-trade-war-officials-093000990.html"},{"t":"White House says China's actions on Micron won't torpedo relations","dt":"01:18PM","a":"Reuters","u":"https:\/\/finance.yahoo.com\/news\/white-house-says-chinas-actions-171819312.html"},{"t":"3 Reasons the Market Yawned at China's Micron Ban","dt":"07:37AM","a":"Motley Fool","u":"https:\/\/finance.yahoo.com\/m\/323579af-fe74-3af6-b393-b74fe7517b43\/3-reasons-the-market-yawned.html"},{"t":"China defends ban on US chipmaker Micron, accuses Washington of 'economic coercion'","dt":"06:54AM","a":"AP Finance","u":"https:\/\/finance.yahoo.com\/news\/china-defends-ban-us-chipmaker-105440624.html"},{"t":"Factbox-US-China tensions intensify over tech to Taiwan flashpoints","dt":"04:21AM","a":"Reuters","u":"https:\/\/finance.yahoo.com\/news\/factbox-us-china-tensions-intensify-082133984.html"},{"t":"China's Micron ban 'not based in fact,' White House says","dt":"05:38PM","a":"Reuters","u":"https:\/\/finance.yahoo.com\/news\/chinas-micron-ban-not-based-213818763.html"},{"t":"Exclusive-US lawmaker demands action against Chinese chip firm CXMT after Micron","dt":"02:52PM","a":"Reuters","u":"https:\/\/finance.yahoo.com\/news\/exclusive-chinese-chip-firm-u-185256534.html"},{"t":"Top US senator, Biden administration work to address China's Micron chips ban","dt":"12:33PM","a":"Reuters","u":"https:\/\/finance.yahoo.com\/news\/top-us-senator-biden-working-163343636.html"},{"t":"Micron Has a China Problem","dt":"06:20AM","a":"Motley Fool","u":"https:\/\/finance.yahoo.com\/m\/66dd364b-33e0-3e3e-a7ea-99ada7c4f46e\/micron-has-a-china-problem.html"},{"t":"Asian stocks dip as Japan rally stalls, debt ceiling uncertainty persists","dt":"May-22-23 08:01PM","a":"Investing.com","u":"https:\/\/finance.yahoo.com\/news\/asian-stocks-dip-japan-rally-000152710.html"},{"t":"MORNING BID ASIA-PMIs could knock stocks off highs","dt":"05:45PM","a":"Reuters","u":"https:\/\/finance.yahoo.com\/news\/morning-bid-asia-pmis-could-214500193.html"},{"t":"These Stocks Are Moving the Most Today: Micron, PDC Energy, PacWest, Plug Power, DraftKings, and More","dt":"04:18PM","a":"Barrons.com","u":"https:\/\/finance.yahoo.com\/m\/09bba31c-5bdd-3066-b39f-d18ba47444db\/these-stocks-are-moving-the.html"},{"t":"Stocks to Watch Monday: Micron, Meta, PDC Energy","dt":"01:04PM","a":"The Wall Street Journal","u":"https:\/\/finance.yahoo.com\/m\/c30cb9e9-c685-3770-ae5c-5f7ad3a83dfe\/stocks-to-watch-monday%3A.html"},{"t":"EU Slaps Meta With Penalty For Data Privacy Violation, Uber's Diversity Leader Faces Heat, China Bans Some Of Micron's Product Sales: Today's Top Stories","dt":"12:20PM","a":"Benzinga","u":"https:\/\/finance.yahoo.com\/news\/eu-slaps-meta-penalty-data-162044687.html"},{"t":"Micron's Shares Slump After China Restricts Sales","dt":"10:45AM","a":"The Wall Street Journal","u":"https:\/\/finance.yahoo.com\/m\/3d0e8122-bad3-3de2-97a1-f0fba5f3102a\/micron%27s-shares-slump-after.html"},{"t":"Stocks: Chevron, PacWest, Micron amongst the morning's top movers","dt":"10:21AM","a":"Yahoo Finance Video","u":"https:\/\/finance.yahoo.com\/video\/stocks-chevron-pacwest-micron-amongst-142107055.html"},{"t":"China bans Micron from projects tied to national security concerns","dt":"09:46AM","a":"Yahoo Finance Video","u":"https:\/\/finance.yahoo.com\/video\/china-bans-micron-projects-tied-134609622.html"}]}